localstack_persistence/__init__.py
localstack_persistence/config.py
localstack_persistence/constants.py
localstack_persistence/manager.py
localstack_persistence/utils.py
localstack_persistence/pickling/__init__.py
localstack_persistence/pickling/__plugins__.py
localstack_persistence/pickling/reducers/__init__.py
localstack_persistence/pickling/reducers/botocore.py
localstack_persistence/pickling/reducers/cryptography.py
localstack_persistence/pickling/reducers/stdlib.py
localstack_persistence/pickling/reducers/services/__init__.py
localstack_persistence/pickling/reducers/services/acm.py
localstack_persistence/pods/__init__.py
localstack_persistence/pods/__plugins__.py
localstack_persistence/pods/endpoints.py
localstack_persistence/pods/load.py
localstack_persistence/pods/manager.py
localstack_persistence/pods/save.py
localstack_persistence/reset/__init__.py
localstack_persistence/reset/__plugins__.py
localstack_persistence/reset/endpoints.py
localstack_persistence/reset/reset.py
localstack_persistence/snapshot/__init__.py
localstack_persistence/snapshot/__plugins__.py
localstack_persistence/snapshot/api.py
localstack_persistence/snapshot/endpoints.py
localstack_persistence/snapshot/load.py
localstack_persistence/snapshot/manager.py
localstack_persistence/snapshot/save.py
localstack_plugin_persistence-1.2.2.dist-info/METADATA
localstack_plugin_persistence-1.2.2.dist-info/WHEEL
localstack_plugin_persistence-1.2.2.dist-info/entry_points.txt
localstack_plugin_persistence-1.2.2.dist-info/plux.json
localstack_plugin_persistence-1.2.2.dist-info/top_level.txt
localstack_plugin_persistence-1.2.2.dist-info/RECORD
