Metadata-Version: 2.1
Name: localstack-plugin-persistence
Version: 1.2.2
Summary: plugin containing persistence code
Home-page: https://github.com/localstack/localstack-plugin-persistence
Author: LocalStack Contributors
Author-email: info@localstack.cloud
Requires-Dist: localstack-core >=2.2.0.dev
Requires-Dist: moto-ext
Provides-Extra: dev
Requires-Dist: black ==23.10.0 ; extra == 'dev'
Requires-Dist: coverage[toml] >=5.0.0 ; extra == 'dev'
Requires-Dist: localstack-core[runtime] >=2.2.0.dev ; extra == 'dev'
Requires-Dist: plux >=1.3.1 ; extra == 'dev'
Requires-Dist: pyproject-flake8 >=6.0.0.post1 ; extra == 'dev'
Requires-Dist: pytest >=7.0 ; extra == 'dev'
Requires-Dist: python-minifier >=2.8.0 ; extra == 'dev'
Requires-Dist: ruff ==0.1.0 ; extra == 'dev'
